<?xml version="1.0" standalone="yes"?>
<DocumentElement>
  <DbConfig.xml>
    <ID>1</ID>
    <serverName>VlYMh4/svfiVfUytF9Kw2Q==</serverName>
    <bWindows>N</bWindows>
    <Uid>Um5Ltp2dNRc=</Uid>
    <Psw>Um5Ltp2dNRc=</Psw>
    <DataBase>a4gt1qbziQk=</DataBase>
  </DbConfig.xml>
  <DbConfig.xml>
    <ID>2</ID>
    <serverName>1W8+UiN1UY4=</serverName>
    <bWindows>Y</bWindows>
    <Uid>0/6CNZ6j9uA=</Uid>
    <Psw>0/6CNZ6j9uA=</Psw>
    <DataBase>tgSw0QvN95U=</DataBase>
  </DbConfig.xml>
</DocumentElement>